flarejax/__init__.py
flarejax/_filter.py
flarejax/_module.py
flarejax/_serial.py
flarejax/_tcheck.py
flarejax/net/__init__.py
flarejax/net/_attention.py
flarejax/net/_combine.py
flarejax/net/_linear.py
flarejax/net/_norm.py
flarejax/net/_transform.py
flarejax/opt/__init__.py
flarejax/opt/_adam.py
flarejax/opt/_opt.py
flarejax/opt/_sgd.py
noxjax-0.4.0.dist-info/METADATA
noxjax-0.4.0.dist-info/WHEEL
noxjax-0.4.0.dist-info/top_level.txt
noxjax-0.4.0.dist-info/RECORD
